sydney/__init__.py
sydney/constants.py
sydney/enums.py
sydney/exceptions.py
sydney/sydney.py
sydney/utils.py
sydney_py-0.23.0.dist-info/LICENSE
sydney_py-0.23.0.dist-info/METADATA
sydney_py-0.23.0.dist-info/WHEEL
sydney_py-0.23.0.dist-info/RECORD
