Metadata-Version: 2.3
Name: sydney-py
Version: 0.23.0
Summary: Python Client for Copilot (formerly named Bing Chat), also known as Sydney.
License: MIT
Author: vsakkas
Author-email: vasileios.sakkas96@gmail.com
Requires-Python: >=3.9,<4.0
Classifier: License :: OSI Approved :: MIT License
Classifier: Programming Language :: Python :: 3
Classifier: Programming Language :: Python :: 3.9
Classifier: Programming Language :: Python :: 3.10
Classifier: Programming Language :: Python :: 3.11
Classifier: Programming Language :: Python :: 3.12
Classifier: Programming Language :: Python :: 3.13
Requires-Dist: aiohttp (>=3.11.11,<4.0.0)
Requires-Dist: brotli (>=1.1.0,<2.0.0)
Requires-Dist: websockets (>=14.1,<15.0)
